flytekitplugins_pandera-1.16.12-py3.14-nspkg.pth
flytekitplugins/pandera/__init__.py
flytekitplugins/pandera/config.py
flytekitplugins/pandera/pandas_renderer.py
flytekitplugins/pandera/pandas_transformer.py
flytekitplugins_pandera-1.16.12.dist-info/METADATA
flytekitplugins_pandera-1.16.12.dist-info/WHEEL
flytekitplugins_pandera-1.16.12.dist-info/entry_points.txt
flytekitplugins_pandera-1.16.12.dist-info/namespace_packages.txt
flytekitplugins_pandera-1.16.12.dist-info/top_level.txt
flytekitplugins_pandera-1.16.12.dist-info/RECORD
